elkplot/__init__.py
elkplot/axidraw.ini
elkplot/calibrate.py
elkplot/cli.py
elkplot/device.py
elkplot/planner.py
elkplot/renderer.py
elkplot/shape_utils.py
elkplot/sizes.py
elkplot/spatial.py
elkplot/svg_load.py
elkplot/text/__init__.py
elkplot/text/hershey.py
elkplot/text/hershey_fonts.py
elkplot/util.py
elkplot-0.1.2.dist-info/entry_points.txt
elkplot-0.1.2.dist-info/LICENSE.md
elkplot-0.1.2.dist-info/METADATA
elkplot-0.1.2.dist-info/WHEEL
elkplot-0.1.2.dist-info/RECORD
