Metadata-Version: 2.1
Name: elkplot
Version: 0.1.2
Summary: A library for making and executing generative art for the Axidraw line of pen plotters.
Author: El Kaplan
Author-email: kaplan.el.j@gmail.com
Requires-Python: >=3.11,<4.0
Classifier: Programming Language :: Python :: 3
Classifier: Programming Language :: Python :: 3.11
Requires-Dist: click (>=8.1.3,<9.0.0)
Requires-Dist: hypothesis (>=6.67.1,<7.0.0)
Requires-Dist: ortools (>=9.5.2237,<10.0.0)
Requires-Dist: pint (>=0.20.1,<0.21.0)
Requires-Dist: pyglet (==1.5.27)
Requires-Dist: pyserial (>=3.5,<4.0)
Requires-Dist: pytest (>=7.2.1,<8.0.0)
Requires-Dist: rtree (>=1.0.1,<2.0.0)
Requires-Dist: shapely (>=2.0.1,<3.0.0)
Requires-Dist: svg-path (>=6.2,<7.0)
Requires-Dist: tqdm (>=4.64.1,<5.0.0)
